MANIFEST.in
README.md
requirements.txt
requirements_tests.txt
setup.py
ipaconnector/__init__.py
ipaconnector/config.py
ipaconnector/connector.py
ipaconnector/constans.py
ipaconnector/jdbc.py
ipaconnector/kerberos.py
ipaconnector/klass.py
ipaconnector/mappings.py
ipaconnector/sshwrapper.py
ipaconnector.egg-info/PKG-INFO
ipaconnector.egg-info/SOURCES.txt
ipaconnector.egg-info/dependency_links.txt
ipaconnector.egg-info/requires.txt
ipaconnector.egg-info/top_level.txt
scripts/ipa-connector
tests/__init__.py
tests/test_basic.py
tests/test_case_five.py
tests/test_case_seven.py
tests/test_case_six.py
tests/test_jdbc.py
tests/test_kerberos.py
tests/test_klass.py
tests/test_sshwrapper.py