Metadata-Version: 2.1
Name: ipaconnector
Version: 0.1.0
Summary: IPA connector
Home-page: UNKNOWN
Author: Michal Grzejszczak
Author-email: michal.grzejszczak@ibm.com
License: UNKNOWN
Platform: UNKNOWN
Classifier: Programming Language :: Python :: 3
Classifier: License :: OSI Approved :: MIT License
Classifier: Operating System :: POSIX :: Linux
Requires-Python: >=3.6
